{
  "token_spans": [
    {
      "text": "30-year-old male",
      "type": "num",
      "severity": "3",
      "char_start": 32,
      "char_end": 48
    }
  ],
  "sentence_labels": {
    "0": {
      "faithful": "Faithful",
      "type": null,
      "severity": "N/A"
    },
    "1": {
      "faithful": "Faithful",
      "type": null,
      "severity": "N/A"
    },
    "2": {
      "faithful": "Faithful",
      "type": null,
      "severity": "N/A"
    },
    "3": {
      "faithful": "Faithful",
      "type": null,
      "severity": "N/A"
    },
    "4": {
      "faithful": "Faithful",
      "type": null,
      "severity": "N/A"
    },
    "5": {
      "faithful": "Faithful",
      "type": null,
      "severity": "N/A"
    },
    "6": {
      "faithful": "Faithful",
      "type": null,
      "severity": "N/A"
    },
    "7": {
      "faithful": "Faithful",
      "type": null,
      "severity": "N/A"
    },
    "8": {
      "faithful": "Faithful",
      "type": null,
      "severity": "N/A"
    },
    "9": {
      "faithful": "Faithful",
      "type": null,
      "severity": "N/A"
    },
    "10": {
      "faithful": "Faithful",
      "type": null,
      "severity": "N/A"
    },
    "11": {
      "faithful": "Faithful",
      "type": null,
      "severity": "N/A"
    },
    "12": {
      "faithful": "Faithful",
      "type": null,
      "severity": "N/A"
    },
    "13": {
      "faithful": "Faithful",
      "type": null,
      "severity": "N/A"
    },
    "14": {
      "faithful": "Faithful",
      "type": null,
      "severity": "N/A"
    },
    "15": {
      "faithful": "Faithful",
      "type": null,
      "severity": "N/A"
    },
    "16": {
      "faithful": "Faithful",
      "type": null,
      "severity": "N/A"
    },
    "17": {
      "faithful": "Faithful",
      "type": null,
      "severity": "N/A"
    },
    "18": {
      "faithful": "Faithful",
      "type": null,
      "severity": "N/A"
    },
    "19": {
      "faithful": "Faithful",
      "type": null,
      "severity": "N/A"
    },
    "21": {
      "faithful": "Faithful",
      "type": null,
      "severity": "N/A"
    },
    "22": {
      "faithful": "Faithful",
      "type": null,
      "severity": "N/A"
    },
    "23": {
      "faithful": "Faithful",
      "type": null,
      "severity": "N/A"
    },
    "24": {
      "faithful": "Faithful",
      "type": null,
      "severity": "N/A"
    },
    "25": {
      "faithful": "Faithful",
      "type": null,
      "severity": "N/A"
    },
    "26": {
      "faithful": "Faithful",
      "type": null,
      "severity": "N/A"
    },
    "27": {
      "faithful": "Faithful",
      "type": null,
      "severity": "N/A"
    },
    "28": {
      "faithful": "Faithful",
      "type": null,
      "severity": "N/A"
    }
  },
  "note_html": "Subjective:\nHPI: The patient, a <span class=\"hl-num\" data-hl-type=\"num\" data-hl-sev=\"3\" data-char-start=\"32\" data-char-end=\"48\" title=\"num \u00b7 severity 3 [32:48]\">30-year-old male</span>, presented with neck pain following a car accident one week ago. He described the pain as a 7 out of 10 in severity, with exacerbation upon movement of the neck. He has tried ibuprofen, which provided some relief, but the pain remains. He reports pain in the back of his neck, with some improvement with ibuprofen, but still a 5 out of 10. He denies any worsening of pain, but reports increased pain with neck movement. He has had headaches but none recently. He denies any hearing or visual disturbances. He has a history of playing football, but no previous neck issues. He did not seek medical attention after the accident due to cost concerns. He denies any swelling or bruising on his neck.\n\nPast medical history: [NOT MENTIONED]\n\nReview of systems: [NOT MENTIONED]\n\nCurrent medications: [NOT MENTIONED]\n\nObjective:\nVital signs: [NOT MENTIONED]\n\nPhysical exam: The patient exhibited positive pain to palpation of the soft tissues of the neck, with exacerbation upon flexion, extension, rotation, and lateral bending. The patient had some difficulty turning his neck from side to side.\n\nTest Results: The patient's x-ray results showed no signs of fracture or bony abnormalities.\n\nAssessment / Problem List:\nAssessment: The patient has neck strain, likely secondary to whiplash from the car accident.\n\nProblem list: Neck strain; Suspected whiplash; [NOT MENTIONED]\n\nPlan:\nI prescribed Motrin 600mg every 6-8 hours for pain management. I also prescribed Flexeril 10mg every 12 hours as needed for muscle relaxation. I advised the patient to avoid straining his neck and to be conservative with movement. I ordered an MRI to rule out any nerve impingement or other complications. I will refer the patient to either physical rehab or a chiropractor for further evaluation and treatment after the MRI results are available.\n\nFollow-up: I will review the MRI results and follow up with the patient to discuss further treatment options."
}