[
  {
    "subjective": [
      "The patient is a 30-year-old female.",
      "The patient has a history of asthma.",
      "The patient experiences frequent asthma exacerbations.",
      "The patient's asthma exacerbations occur when she gets sick with a cold.",
      "The patient's asthma exacerbations occur when exposed to her aunt's cat.",
      "The patient uses her albuterol inhaler daily.",
      "The patient takes two puffs of albuterol every 4-6 hours as needed.",
      "The patient occasionally uses steroids.",
      "The patient had several urgent care visits in the past year.",
      "The patient had one emergency department visit in the past year.",
      "The patient's most recent asthma exacerbation occurred about a month ago.",
      "The patient denies smoking.",
      "The patient denies vaping.",
      "The patient denies marijuana use.",
      "The patient has no history of seasonal allergies.",
      "The patient enjoys hiking.",
      "The patient enjoys outdoor activities.",
      "The patient has to be careful with outdoor activities due to asthma symptoms.",
      "The patient was hospitalized for asthma at age 8.",
      "The patient reports coughing symptoms.",
      "The patient reports wheezing symptoms.",
      "The patient denies other symptoms in other organs.",
      "The doctor prescribed Ventolin.",
      "The Ventolin dose is 2 puffs.",
      "Ventolin is taken every 4-6 hours.",
      "Ventolin is taken as needed.",
      "Ventolin is prescribed for asthma.",
      "The doctor prescribed Flovent.",
      "The Flovent dose is 110 micrograms.",
      "The Flovent dose is 1 puff.",
      "Flovent is taken twice per day.",
      "Flovent is prescribed for asthma.",
      "The patient had multiple urgent care visits in the past year.",
      "The patient had one emergency department visit in the past year."
    ],
    "objective": [
      "The patient's blood pressure is 128/82.",
      "The patient's pulse rate is 16.",
      "The patient's oxygen saturation is 99%.",
      "The patient's oxygen saturation was measured on room air.",
      "The patient's respiratory rate is 16.",
      "The patient has diminished lung sounds throughout.",
      "The patient has occasional slight expiratory wheeze bilaterally.",
      "The trachea is midline.",
      "The patient denied lymphadenopathy.",
      "The patient denied carotid bruit.",
      "The patient has strong bilateral pulses.",
      "The patient denied clubbing on fingertips.",
      "The patient has brisk capillary refill.",
      "The pulmonary function test results are consistent with asthma.",
      "The patient has asthma."
    ],
    "assessment": [
      "The patient has moderate intermittent asthma.",
      "The asthma is confirmed by pulmonary function test results.",
      "The asthma is confirmed by clinical presentation.",
      "The patient has a history of asthma hospitalization.",
      "The history of asthma hospitalization is past.",
      "The patient has a history of asthma exacerbations.",
      "The history of asthma exacerbations is active.",
      "Asthma is active."
    ],
    "plan": [
      "The doctor prescribed Flovent.",
      "The Flovent dose is 110 micrograms.",
      "Flovent is taken 1 puff twice per day.",
      "Flovent is prescribed to help prevent daily symptoms.",
      "Flovent is prescribed to reduce the need for rescue inhaler use.",
      "The doctor prescribed Ventolin.",
      "The Ventolin dose is 2 puffs.",
      "Ventolin is taken every 4-6 hours.",
      "Ventolin is taken as needed.",
      "Ventolin is prescribed for acute exacerbations.",
      "The doctor will create an asthma action plan.",
      "The asthma action plan is to help manage symptoms.",
      "The asthma action plan is to identify triggers.",
      "The patient will be seen in 30 days.",
      "The purpose of the follow-up is to reassess symptoms.",
      "The purpose of the follow-up is to adjust treatment as needed."
    ]
  },
  {
    "subjective": [
      "The patient is a 20-year-old female.",
      "The patient has a history of chronic asthma symptoms.",
      "The patient experiences coughing.",
      "The patient experiences wheezing.",
      "The patient's asthma symptoms occur almost daily.",
      "The patient has frequent exacerbations.",
      "The patient's symptoms worsen with exposure to her aunt's cat.",
      "The patient has been experiencing asthma symptoms for the past six months.",
      "The patient has had frequent visits to urgent care.",
      "The patient has had frequent visits to the emergency department.",
      "The patient has been prescribed steroids.",
      "The patient has been prescribed antibiotics.",
      "The patient uses an albuterol inhaler (Ventolin) daily.",
      "The patient uses two puffs of the albuterol inhaler (Ventolin) almost every day.",
      "The patient uses the albuterol inhaler (Ventolin) occasionally at nighttime.",
      "The patient has a history of asthma.",
      "The patient has been using an albuterol inhaler (Ventolin) daily for asthma.",
      "The patient was hospitalized for asthma at the age of 8 years.",
      "The patient has not been hospitalized for asthma since the age of 8 years.",
      "The patient has no other significant medical conditions.",
      "The patient has no allergies.",
      "The patient denied other symptoms except for asthma symptoms.",
      "The doctor prescribed Albuterol inhaler (Ventolin).",
      "The Albuterol inhaler (Ventolin) dose is 2 puffs.",
      "The Albuterol inhaler (Ventolin) is taken every 4-6 hours as needed.",
      "The Albuterol inhaler (Ventolin) is prescribed for rescue.",
      "The doctor prescribed Flovent.",
      "The Flovent dose is 110 micrograms.",
      "The Flovent is taken 1 puff twice daily.",
      "The Flovent is prescribed for inhaled steroid."
    ],
    "objective": [
      "The patient's blood pressure is 128/82 mmHg.",
      "The patient's respiratory rate is 16.",
      "The patient's oxygen saturation is 99% on room air.",
      "The patient has diminished lung sounds.",
      "The patient has occasional slight expiratory wheeze.",
      "The wheeze is bilateral.",
      "The patient's neck is supple.",
      "The patient's trachea is midline.",
      "The patient denied lymphadenopathy.",
      "The patient denied carotid bruit.",
      "The patient has strong bilateral pulses.",
      "The patient denied clubbing.",
      "The patient has brisk capillary refill.",
      "The pulmonary function test results are consistent with asthma.",
      "The patient has asthma."
    ],
    "assessment": [
      "The patient has asthma.",
      "The asthma is moderate.",
      "The asthma is intermittent.",
      "The diagnosis is asthma."
    ],
    "plan": [
      "The doctor prescribed Flovent.",
      "The Flovent dose is 110 micrograms.",
      "Flovent is taken 1 puff twice daily.",
      "Flovent is prescribed for inhaled steroid.",
      "The purpose of Flovent is to help prevent daily symptoms.",
      "The purpose of Flovent is to reduce the need for rescue medication.",
      "The patient is using Ventolin.",
      "The Ventolin dose is 2 puffs.",
      "Ventolin is taken every 4-6 hours.",
      "Ventolin is taken as needed.",
      "Ventolin is used for rescue.",
      "The doctor created an asthma action plan.",
      "The purpose of the asthma action plan is to help manage symptoms.",
      "The purpose of the asthma action plan is to identify triggers.",
      "The patient has a follow-up appointment in 30 days.",
      "The purpose of the follow-up appointment is to review progress.",
      "The purpose of the follow-up appointment is to adjust the treatment plan as needed."
    ]
  },
  {
    "subjective": [
      "The patient is a 30-year-old female.",
      "The patient presents with symptoms of asthma.",
      "The patient experiences frequent coughing.",
      "The patient experiences wheezing.",
      "The patient's symptoms worsen when she gets sick.",
      "The patient's symptoms worsen with a cold.",
      "Exposure to her aunt's cat triggers asthma flare-ups.",
      "The patient has had multiple urgent care visits for asthma symptoms.",
      "The patient has had multiple primary care visits for asthma symptoms.",
      "The patient has received steroid treatment for asthma symptoms.",
      "The patient uses a blue inhaler (ventolin) daily.",
      "The patient uses ventolin for asthma.",
      "The ventolin dose is 2 puffs.",
      "Ventolin is taken as needed.",
      "The patient was hospitalized for asthma at age 8.",
      "The patient has not been hospitalized for asthma since age 8.",
      "The patient denies other symptoms in other organs.",
      "The patient experiences breathing difficulties when exposed to cigarette smoke.",
      "The patient experiences breathing difficulties in bars.",
      "The patient uses ventolin almost daily.",
      "The patient uses ventolin at night occasionally.",
      "The patient uses ventolin a couple of times a week."
    ],
    "objective": [
      "The patient's blood pressure is 128/82.",
      "The patient's respiratory rate is 16.",
      "The patient's oxygen saturation is 99%.",
      "The patient's oxygen saturation was measured on room air.",
      "The patient has diminished lung sounds.",
      "The patient has occasional slight expiratory wheeze.",
      "The expiratory wheeze is bilateral.",
      "The patient's neck exam is supple.",
      "The patient has a midline trachea.",
      "The patient denied lymphadenopathy.",
      "The carotid bruit is not appreciated.",
      "The patient has strong bilateral pulses.",
      "The patient denied clubbing on her fingertips.",
      "The patient has brisk capillary refill.",
      "The pulmonary function test results are consistent with asthma.",
      "The patient has asthma."
    ],
    "assessment": [
      "The patient has symptoms consistent with asthma.",
      "The patient's asthma is moderate.",
      "The patient's asthma is intermittent.",
      "The patient has been assessed."
    ],
    "plan": [
      "The doctor prescribed Flovent.",
      "The Flovent dose is 110 micrograms.",
      "Flovent is taken one puff twice a day.",
      "Flovent is prescribed to prevent daily symptoms.",
      "Flovent is prescribed to reduce the need for a rescue inhaler.",
      "The patient can use her Ventolin inhaler as needed.",
      "The doctor prescribed Ventolin.",
      "The Ventolin dose is 2 puffs.",
      "Ventolin is taken every 4-6 hours.",
      "The doctor will create an asthma action plan.",
      "The asthma action plan is to manage symptoms.",
      "The asthma action plan is to identify triggers.",
      "The patient has a follow-up appointment in a month.",
      "The patient should have a follow-up appointment sooner if symptoms worsen."
    ]
  }
]